shipyard_hightouch/__init__.py
shipyard_hightouch/cli/authtest.py
shipyard_hightouch/cli/check_sync_cli.py
shipyard_hightouch/cli/trigger_sync_cli.py
shipyard_hightouch/hightouch.py
shipyard_hightouch-0.1.1.dist-info/METADATA
shipyard_hightouch-0.1.1.dist-info/WHEEL
shipyard_hightouch-0.1.1.dist-info/RECORD
